aqara_iot/__init__.py
aqara_iot/aqara_enums.py
aqara_iot/device.py
aqara_iot/home.py
aqara_iot/openapi.py
aqara_iot/openlogging.py
aqara_iot/openmq.py
aqara_iot/version.py
aqara_iot_py_sdk-1.0.9.dist-info/LICENSE
aqara_iot_py_sdk-1.0.9.dist-info/METADATA
aqara_iot_py_sdk-1.0.9.dist-info/WHEEL
aqara_iot_py_sdk-1.0.9.dist-info/entry_points.txt
aqara_iot_py_sdk-1.0.9.dist-info/top_level.txt
aqara_iot_py_sdk-1.0.9.dist-info/RECORD
