Metadata-Version: 2.1
Name: aqara-iot-py-sdk
Version: 1.0.9
Summary: A Python sdk for Aqara Open API, which provides IoT capabilities, maintained by Aqara official
Home-page: https://github.com/aqara/aqara-iot-app-sdk-python
Author: Aqara Inc.
Author-email: developer@aqara.com
License: MIT
Project-URL: Bug Tracker, https://github.com/aqara/aqara-iot-app-sdk-python/issues
Project-URL: Changes, https://github.com/aqara/aqara-iot-python-sdk/wiki/Aqara-IoT-Python-SDK-Release-Notes
Keywords: aqara iot app sdk python
Platform: UNKNOWN
Classifier: Development Status :: 4 - Beta
Classifier: License :: OSI Approved :: MIT License
Classifier: Operating System :: OS Independent
Classifier: Topic :: Software Development
Classifier: Programming Language :: Python :: 3
Classifier: Programming Language :: Python :: 3.7
Classifier: Programming Language :: Python :: 3.8
Classifier: Programming Language :: Python :: 3.9
Classifier: Programming Language :: Python :: 3.10
Classifier: Programming Language :: Python :: Implementation :: PyPy
Requires-Python: >=3.7
License-File: LICENSE
Requires-Dist: paho-mqtt
Requires-Dist: requests
Requires-Dist: pycryptodome
Requires-Dist: websocket-client
